LICENSE
MANIFEST.in
README.rst
setup.py
django_notifyme.egg-info/PKG-INFO
django_notifyme.egg-info/SOURCES.txt
django_notifyme.egg-info/dependency_links.txt
django_notifyme.egg-info/not-zip-safe
django_notifyme.egg-info/top_level.txt
notifyme/__init__.py
notifyme/api.py
notifyme/models.py
notifyme/tasks.py
notifyme/delivery_backends/__init__.py
notifyme/delivery_backends/base.py
notifyme/notification_types/__init__.py
notifyme/notification_types/base.py
notifyme/notification_types/printer_on_fire.py
notifyme/templates/notifyme/notification_types/printer_on_fire/email/body.html
notifyme/templates/notifyme/notification_types/printer_on_fire/email/body.txt
notifyme/templates/notifyme/notification_types/printer_on_fire/email/subject.txt
notifyme/templates/notifyme/notification_types/printer_on_fire/onsite/sticky_body.html